README.md
setup.cfg
setup.py
paystack/__init__.py
paystack/api_client.py
paystack/configuration.py
paystack/exceptions.py
paystack/rest.py
paystack/api/__init__.py
paystack/api/balance_.py
paystack/api/bulk_charge_.py
paystack/api/charge_.py
paystack/api/customer_.py
paystack/api/dedicated_virtual_account_.py
paystack/api/dispute_.py
paystack/api/integration_.py
paystack/api/page_.py
paystack/api/payment_request_.py
paystack/api/plan_.py
paystack/api/product_.py
paystack/api/refund_.py
paystack/api/settlement_.py
paystack/api/split_.py
paystack/api/subaccount_.py
paystack/api/subscription_.py
paystack/api/transaction_.py
paystack/api/transfer_.py
paystack/api/transfer_recipient_.py
paystack/api/verification_.py
paystack/models/__init__.py
paystack/models/accepted.py
paystack/models/bank.py
paystack/models/bulk_charge_initiate.py
paystack/models/charge_create.py
paystack/models/charge_submit_address.py
paystack/models/charge_submit_birthday.py
paystack/models/charge_submit_otp.py
paystack/models/charge_submit_phone.py
paystack/models/charge_submit_pin.py
paystack/models/customer_create.py
paystack/models/customer_deactivate_authorization.py
paystack/models/customer_risk_action.py
paystack/models/customer_update.py
paystack/models/customer_validate.py
paystack/models/customer_validation.py
paystack/models/dedicated_virtual_account_create.py
paystack/models/dedicated_virtual_account_split.py
paystack/models/dispute_evidence.py
paystack/models/dispute_resolve.py
paystack/models/dispute_update.py
paystack/models/eft.py
paystack/models/error.py
paystack/models/mobile_money.py
paystack/models/page_create.py
paystack/models/page_product.py
paystack/models/page_update.py
paystack/models/payment_request_create.py
paystack/models/payment_request_update.py
paystack/models/plan_create.py
paystack/models/plan_update.py
paystack/models/product_create.py
paystack/models/product_update.py
paystack/models/refund_create.py
paystack/models/response.py
paystack/models/split_create.py
paystack_sdk.egg-info/PKG-INFO
paystack_sdk.egg-info/SOURCES.txt
paystack_sdk.egg-info/dependency_links.txt
paystack_sdk.egg-info/requires.txt
paystack_sdk.egg-info/top_level.txt
