Metadata-Version: 1.0
Name: paystack-sdk
Version: 1.0.0b1
Summary: Paystack
Home-page: https://github.com/PaystackOSS/paystack-python
Author: Paystack Integration
Author-email: techsupport@paystack.com
License: UNKNOWN
Keywords: Paystack,Transaction,Split Payment,Customer,Dedicated Virtual Account,Subaccount,Plan,Subscription,Product,Page,Payment Request,Settlement,Transfer Recipient,Transfer,Balance,Charge,Bulk Charge,Integration,Refund,Dispute,Verification
Platform: UNKNOWN
